{
    "meta_data": {
        "is_multitask": false,
        "target_predicates": [
            "perp"
        ]
    },
    "data": {
        "train": {
            "background_knowledge": [
                "perp(A0, B0, A0, C0)",
                "cong(A0, B0, A0, C0)",
                "cong(D0, C0, D0, B0)",
                "coll(B0, D0, C0)",
                "ncoll(A0, C0, D0)",
                "cong(C0, A0, C0, E0)",
                "coll(E0, B0, C0)",
                "ncoll(C0, A0, E0)",
                "cong(A0, F0, A0, D0)",
                "coll(A0, B0, F0)",
                "perp(A1, B1, A1, C1)",
                "cong(A1, B1, A1, C1)",
                "cong(D1, C1, D1, B1)",
                "coll(B1, D1, C1)",
                "ncoll(A1, C1, D1)",
                "cong(C1, A1, C1, E1)",
                "coll(E1, B1, C1)",
                "ncoll(C1, A1, E1)",
                "cong(A1, F1, A1, D1)",
                "coll(A1, B1, F1)",
                "perp(A2, B2, A2, C2)",
                "cong(A2, B2, A2, C2)",
                "cong(D2, C2, D2, B2)",
                "coll(B2, D2, C2)",
                "ncoll(A2, C2, D2)",
                "cong(C2, A2, C2, E2)",
                "coll(E2, B2, C2)",
                "ncoll(C2, A2, E2)",
                "cong(A2, F2, A2, D2)",
                "coll(A2, B2, F2)",
                "perp(A3, B3, A3, C3)",
                "cong(A3, B3, A3, C3)",
                "cong(D3, C3, D3, B3)",
                "coll(B3, D3, C3)",
                "ncoll(A3, C3, D3)",
                "cong(C3, A3, C3, E3)",
                "coll(E3, B3, C3)",
                "ncoll(C3, A3, E3)",
                "cong(A3, F3, A3, D3)",
                "coll(A3, B3, F3)",
                "perp(A4, B4, A4, C4)",
                "cong(A4, B4, A4, C4)",
                "cong(D4, C4, D4, B4)",
                "coll(B4, D4, C4)",
                "ncoll(A4, C4, D4)",
                "cong(C4, A4, C4, E4)",
                "coll(E4, B4, C4)",
                "ncoll(C4, A4, E4)",
                "cong(A4, F4, A4, D4)",
                "coll(A4, B4, F4)",
                "perp(A5, B5, A5, C5)",
                "cong(A5, B5, A5, C5)",
                "cong(D5, C5, D5, B5)",
                "coll(B5, D5, C5)",
                "ncoll(A5, C5, D5)",
                "cong(C5, A5, C5, E5)",
                "coll(E5, B5, C5)",
                "ncoll(C5, A5, E5)",
                "cong(A5, F5, A5, D5)",
                "coll(A5, B5, F5)",
                "perp(A6, B6, A6, C6)",
                "cong(A6, B6, A6, C6)",
                "cong(D6, C6, D6, B6)",
                "coll(B6, D6, C6)",
                "ncoll(A6, C6, D6)",
                "cong(C6, A6, C6, E6)",
                "coll(E6, B6, C6)",
                "ncoll(C6, A6, E6)",
                "cong(A6, F6, A6, D6)",
                "coll(A6, B6, F6)",
                "perp(A7, B7, A7, C7)",
                "cong(A7, B7, A7, C7)",
                "cong(D7, C7, D7, B7)",
                "coll(B7, D7, C7)",
                "ncoll(A7, C7, D7)",
                "cong(C7, A7, C7, E7)",
                "coll(E7, B7, C7)",
                "ncoll(C7, A7, E7)",
                "cong(A7, F7, A7, D7)",
                "coll(A7, B7, F7)"
            ],
            "positive_examples": [
                "perp(B0, C0, A0, D0)",
                "perp(D0, F0, A0, E0)",
                "perp(B1, C1, A1, D1)",
                "perp(D1, F1, A1, E1)",
                "perp(B2, C2, A2, D2)",
                "perp(D2, F2, A2, E2)",
                "perp(B3, C3, A3, D3)",
                "perp(D3, F3, A3, E3)",
                "perp(B4, C4, A4, D4)",
                "perp(D4, F4, A4, E4)",
                "perp(B5, C5, A5, D5)",
                "perp(D5, F5, A5, E5)",
                "perp(B6, C6, A6, D6)",
                "perp(D6, F6, A6, E6)",
                "perp(B7, C7, A7, D7)",
                "perp(D7, F7, A7, E7)"
            ],
            "proof_steps": [
                {
                    "body": [
                        "cong(A0, B0, A0, C0)",
                        "cong(D0, C0, D0, B0)"
                    ],
                    "head": "perp(B0, C0, A0, D0)"
                },
                {
                    "body": [
                        "cong(C0, A0, C0, E0)",
                        "cong(A0, F0, A0, D0)"
                    ],
                    "head": "eqratio(C0, A0, C0, E0, A0, F0, A0, D0)"
                },
                {
                    "body": [
                        "coll(E0, B0, C0)"
                    ],
                    "head": "coll(C0, E0, B0)"
                },
                {
                    "body": [
                        "coll(A0, B0, F0)"
                    ],
                    "head": "coll(A0, F0, B0)"
                },
                {
                    "body": [
                        "coll(B0, D0, C0)",
                        "cong(D0, C0, D0, B0)"
                    ],
                    "head": "midp(D0, C0, B0)"
                },
                {
                    "body": [
                        "perp(A0, B0, A0, C0)",
                        "midp(D0, C0, B0)"
                    ],
                    "head": "cong(C0, D0, A0, D0)"
                },
                {
                    "body": [
                        "perp(A0, B0, A0, C0)",
                        "midp(D0, C0, B0)"
                    ],
                    "head": "cong(B0, D0, A0, D0)"
                },
                {
                    "body": [
                        "cong(A0, B0, A0, C0)",
                        "cong(C0, D0, A0, D0)",
                        "cong(B0, D0, A0, D0)",
                        "ncoll(A0, C0, D0)"
                    ],
                    "head": "eqangle(C0, A0, C0, D0, A0, B0, A0, D0)"
                },
                {
                    "body": [
                        "eqangle(C0, A0, C0, D0, A0, B0, A0, D0)",
                        "coll(B0, D0, C0)"
                    ],
                    "head": "eqangle(A0, C0, B0, C0, A0, B0, A0, D0)"
                },
                {
                    "body": [
                        "coll(C0, E0, B0)",
                        "coll(A0, F0, B0)",
                        "eqangle(A0, C0, B0, C0, A0, B0, A0, D0)"
                    ],
                    "head": "eqangle(C0, A0, C0, E0, A0, F0, A0, D0)"
                },
                {
                    "body": [
                        "eqratio(C0, A0, C0, E0, A0, F0, A0, D0)",
                        "eqangle(C0, A0, C0, E0, A0, F0, A0, D0)",
                        "ncoll(C0, A0, E0)"
                    ],
                    "head": "eqangle(E0, A0, E0, C0, D0, F0, D0, A0)"
                },
                {
                    "body": [
                        "eqangle(E0, A0, E0, C0, D0, F0, D0, A0)",
                        "coll(E0, B0, C0)"
                    ],
                    "head": "eqangle(A0, E0, D0, F0, B0, C0, A0, D0)"
                },
                {
                    "body": [
                        "cong(A0, B0, A0, C0)",
                        "cong(C0, D0, A0, D0)",
                        "cong(B0, D0, A0, D0)",
                        "ncoll(A0, C0, D0)"
                    ],
                    "head": "eqangle(A0, C0, A0, D0, B0, A0, B0, D0)"
                },
                {
                    "body": [
                        "eqangle(A0, C0, A0, D0, B0, A0, B0, D0)",
                        "coll(B0, D0, C0)"
                    ],
                    "head": "eqangle(A0, B0, A0, C0, B0, C0, A0, D0)"
                },
                {
                    "body": [
                        "eqratio(C0, A0, C0, E0, A0, F0, A0, D0)",
                        "eqangle(C0, A0, C0, E0, A0, F0, A0, D0)",
                        "ncoll(C0, A0, E0)"
                    ],
                    "head": "eqangle(A0, C0, A0, E0, F0, A0, F0, D0)"
                },
                {
                    "body": [
                        "eqangle(A0, C0, A0, E0, F0, A0, F0, D0)",
                        "coll(A0, B0, F0)"
                    ],
                    "head": "eqangle(A0, B0, A0, C0, D0, F0, A0, E0)"
                },
                {
                    "body": [
                        "eqangle(A0, E0, D0, F0, B0, C0, A0, D0)",
                        "eqangle(A0, B0, A0, C0, B0, C0, A0, D0)",
                        "eqangle(A0, B0, A0, C0, D0, F0, A0, E0)"
                    ],
                    "head": "perp(D0, F0, A0, E0)"
                },
                {
                    "body": [
                        "cong(A1, B1, A1, C1)",
                        "cong(D1, C1, D1, B1)"
                    ],
                    "head": "perp(B1, C1, A1, D1)"
                },
                {
                    "body": [
                        "cong(C1, A1, C1, E1)",
                        "cong(A1, F1, A1, D1)"
                    ],
                    "head": "eqratio(C1, A1, C1, E1, A1, F1, A1, D1)"
                },
                {
                    "body": [
                        "coll(E1, B1, C1)"
                    ],
                    "head": "coll(C1, E1, B1)"
                },
                {
                    "body": [
                        "coll(A1, B1, F1)"
                    ],
                    "head": "coll(A1, F1, B1)"
                },
                {
                    "body": [
                        "coll(B1, D1, C1)",
                        "cong(D1, C1, D1, B1)"
                    ],
                    "head": "midp(D1, C1, B1)"
                },
                {
                    "body": [
                        "perp(A1, B1, A1, C1)",
                        "midp(D1, C1, B1)"
                    ],
                    "head": "cong(C1, D1, A1, D1)"
                },
                {
                    "body": [
                        "perp(A1, B1, A1, C1)",
                        "midp(D1, C1, B1)"
                    ],
                    "head": "cong(B1, D1, A1, D1)"
                },
                {
                    "body": [
                        "cong(A1, B1, A1, C1)",
                        "cong(C1, D1, A1, D1)",
                        "cong(B1, D1, A1, D1)",
                        "ncoll(A1, C1, D1)"
                    ],
                    "head": "eqangle(C1, A1, C1, D1, A1, B1, A1, D1)"
                },
                {
                    "body": [
                        "eqangle(C1, A1, C1, D1, A1, B1, A1, D1)",
                        "coll(B1, D1, C1)"
                    ],
                    "head": "eqangle(A1, C1, B1, C1, A1, B1, A1, D1)"
                },
                {
                    "body": [
                        "coll(C1, E1, B1)",
                        "coll(A1, F1, B1)",
                        "eqangle(A1, C1, B1, C1, A1, B1, A1, D1)"
                    ],
                    "head": "eqangle(C1, A1, C1, E1, A1, F1, A1, D1)"
                },
                {
                    "body": [
                        "eqratio(C1, A1, C1, E1, A1, F1, A1, D1)",
                        "eqangle(C1, A1, C1, E1, A1, F1, A1, D1)",
                        "ncoll(C1, A1, E1)"
                    ],
                    "head": "eqangle(E1, A1, E1, C1, D1, F1, D1, A1)"
                },
                {
                    "body": [
                        "eqangle(E1, A1, E1, C1, D1, F1, D1, A1)",
                        "coll(E1, B1, C1)"
                    ],
                    "head": "eqangle(A1, E1, D1, F1, B1, C1, A1, D1)"
                },
                {
                    "body": [
                        "cong(A1, B1, A1, C1)",
                        "cong(C1, D1, A1, D1)",
                        "cong(B1, D1, A1, D1)",
                        "ncoll(A1, C1, D1)"
                    ],
                    "head": "eqangle(A1, C1, A1, D1, B1, A1, B1, D1)"
                },
                {
                    "body": [
                        "eqangle(A1, C1, A1, D1, B1, A1, B1, D1)",
                        "coll(B1, D1, C1)"
                    ],
                    "head": "eqangle(A1, B1, A1, C1, B1, C1, A1, D1)"
                },
                {
                    "body": [
                        "eqratio(C1, A1, C1, E1, A1, F1, A1, D1)",
                        "eqangle(C1, A1, C1, E1, A1, F1, A1, D1)",
                        "ncoll(C1, A1, E1)"
                    ],
                    "head": "eqangle(A1, C1, A1, E1, F1, A1, F1, D1)"
                },
                {
                    "body": [
                        "eqangle(A1, C1, A1, E1, F1, A1, F1, D1)",
                        "coll(A1, B1, F1)"
                    ],
                    "head": "eqangle(A1, B1, A1, C1, D1, F1, A1, E1)"
                },
                {
                    "body": [
                        "eqangle(A1, E1, D1, F1, B1, C1, A1, D1)",
                        "eqangle(A1, B1, A1, C1, B1, C1, A1, D1)",
                        "eqangle(A1, B1, A1, C1, D1, F1, A1, E1)"
                    ],
                    "head": "perp(D1, F1, A1, E1)"
                },
                {
                    "body": [
                        "cong(A2, B2, A2, C2)",
                        "cong(D2, C2, D2, B2)"
                    ],
                    "head": "perp(B2, C2, A2, D2)"
                },
                {
                    "body": [
                        "cong(C2, A2, C2, E2)",
                        "cong(A2, F2, A2, D2)"
                    ],
                    "head": "eqratio(C2, A2, C2, E2, A2, F2, A2, D2)"
                },
                {
                    "body": [
                        "coll(E2, B2, C2)"
                    ],
                    "head": "coll(C2, E2, B2)"
                },
                {
                    "body": [
                        "coll(A2, B2, F2)"
                    ],
                    "head": "coll(A2, F2, B2)"
                },
                {
                    "body": [
                        "coll(B2, D2, C2)",
                        "cong(D2, C2, D2, B2)"
                    ],
                    "head": "midp(D2, C2, B2)"
                },
                {
                    "body": [
                        "perp(A2, B2, A2, C2)",
                        "midp(D2, C2, B2)"
                    ],
                    "head": "cong(C2, D2, A2, D2)"
                },
                {
                    "body": [
                        "perp(A2, B2, A2, C2)",
                        "midp(D2, C2, B2)"
                    ],
                    "head": "cong(B2, D2, A2, D2)"
                },
                {
                    "body": [
                        "cong(A2, B2, A2, C2)",
                        "cong(C2, D2, A2, D2)",
                        "cong(B2, D2, A2, D2)",
                        "ncoll(A2, C2, D2)"
                    ],
                    "head": "eqangle(C2, A2, C2, D2, A2, B2, A2, D2)"
                },
                {
                    "body": [
                        "eqangle(C2, A2, C2, D2, A2, B2, A2, D2)",
                        "coll(B2, D2, C2)"
                    ],
                    "head": "eqangle(A2, C2, B2, C2, A2, B2, A2, D2)"
                },
                {
                    "body": [
                        "coll(C2, E2, B2)",
                        "coll(A2, F2, B2)",
                        "eqangle(A2, C2, B2, C2, A2, B2, A2, D2)"
                    ],
                    "head": "eqangle(C2, A2, C2, E2, A2, F2, A2, D2)"
                },
                {
                    "body": [
                        "eqratio(C2, A2, C2, E2, A2, F2, A2, D2)",
                        "eqangle(C2, A2, C2, E2, A2, F2, A2, D2)",
                        "ncoll(C2, A2, E2)"
                    ],
                    "head": "eqangle(E2, A2, E2, C2, D2, F2, D2, A2)"
                },
                {
                    "body": [
                        "eqangle(E2, A2, E2, C2, D2, F2, D2, A2)",
                        "coll(E2, B2, C2)"
                    ],
                    "head": "eqangle(A2, E2, D2, F2, B2, C2, A2, D2)"
                },
                {
                    "body": [
                        "cong(A2, B2, A2, C2)",
                        "cong(C2, D2, A2, D2)",
                        "cong(B2, D2, A2, D2)",
                        "ncoll(A2, C2, D2)"
                    ],
                    "head": "eqangle(A2, C2, A2, D2, B2, A2, B2, D2)"
                },
                {
                    "body": [
                        "eqangle(A2, C2, A2, D2, B2, A2, B2, D2)",
                        "coll(B2, D2, C2)"
                    ],
                    "head": "eqangle(A2, B2, A2, C2, B2, C2, A2, D2)"
                },
                {
                    "body": [
                        "eqratio(C2, A2, C2, E2, A2, F2, A2, D2)",
                        "eqangle(C2, A2, C2, E2, A2, F2, A2, D2)",
                        "ncoll(C2, A2, E2)"
                    ],
                    "head": "eqangle(A2, C2, A2, E2, F2, A2, F2, D2)"
                },
                {
                    "body": [
                        "eqangle(A2, C2, A2, E2, F2, A2, F2, D2)",
                        "coll(A2, B2, F2)"
                    ],
                    "head": "eqangle(A2, B2, A2, C2, D2, F2, A2, E2)"
                },
                {
                    "body": [
                        "eqangle(A2, E2, D2, F2, B2, C2, A2, D2)",
                        "eqangle(A2, B2, A2, C2, B2, C2, A2, D2)",
                        "eqangle(A2, B2, A2, C2, D2, F2, A2, E2)"
                    ],
                    "head": "perp(D2, F2, A2, E2)"
                },
                {
                    "body": [
                        "cong(A3, B3, A3, C3)",
                        "cong(D3, C3, D3, B3)"
                    ],
                    "head": "perp(B3, C3, A3, D3)"
                },
                {
                    "body": [
                        "cong(C3, A3, C3, E3)",
                        "cong(A3, F3, A3, D3)"
                    ],
                    "head": "eqratio(C3, A3, C3, E3, A3, F3, A3, D3)"
                },
                {
                    "body": [
                        "coll(E3, B3, C3)"
                    ],
                    "head": "coll(C3, E3, B3)"
                },
                {
                    "body": [
                        "coll(A3, B3, F3)"
                    ],
                    "head": "coll(A3, F3, B3)"
                },
                {
                    "body": [
                        "coll(B3, D3, C3)",
                        "cong(D3, C3, D3, B3)"
                    ],
                    "head": "midp(D3, C3, B3)"
                },
                {
                    "body": [
                        "perp(A3, B3, A3, C3)",
                        "midp(D3, C3, B3)"
                    ],
                    "head": "cong(C3, D3, A3, D3)"
                },
                {
                    "body": [
                        "perp(A3, B3, A3, C3)",
                        "midp(D3, C3, B3)"
                    ],
                    "head": "cong(B3, D3, A3, D3)"
                },
                {
                    "body": [
                        "cong(A3, B3, A3, C3)",
                        "cong(C3, D3, A3, D3)",
                        "cong(B3, D3, A3, D3)",
                        "ncoll(A3, C3, D3)"
                    ],
                    "head": "eqangle(C3, A3, C3, D3, A3, B3, A3, D3)"
                },
                {
                    "body": [
                        "eqangle(C3, A3, C3, D3, A3, B3, A3, D3)",
                        "coll(B3, D3, C3)"
                    ],
                    "head": "eqangle(A3, C3, B3, C3, A3, B3, A3, D3)"
                },
                {
                    "body": [
                        "coll(C3, E3, B3)",
                        "coll(A3, F3, B3)",
                        "eqangle(A3, C3, B3, C3, A3, B3, A3, D3)"
                    ],
                    "head": "eqangle(C3, A3, C3, E3, A3, F3, A3, D3)"
                },
                {
                    "body": [
                        "eqratio(C3, A3, C3, E3, A3, F3, A3, D3)",
                        "eqangle(C3, A3, C3, E3, A3, F3, A3, D3)",
                        "ncoll(C3, A3, E3)"
                    ],
                    "head": "eqangle(E3, A3, E3, C3, D3, F3, D3, A3)"
                },
                {
                    "body": [
                        "eqangle(E3, A3, E3, C3, D3, F3, D3, A3)",
                        "coll(E3, B3, C3)"
                    ],
                    "head": "eqangle(A3, E3, D3, F3, B3, C3, A3, D3)"
                },
                {
                    "body": [
                        "cong(A3, B3, A3, C3)",
                        "cong(C3, D3, A3, D3)",
                        "cong(B3, D3, A3, D3)",
                        "ncoll(A3, C3, D3)"
                    ],
                    "head": "eqangle(A3, C3, A3, D3, B3, A3, B3, D3)"
                },
                {
                    "body": [
                        "eqangle(A3, C3, A3, D3, B3, A3, B3, D3)",
                        "coll(B3, D3, C3)"
                    ],
                    "head": "eqangle(A3, B3, A3, C3, B3, C3, A3, D3)"
                },
                {
                    "body": [
                        "eqratio(C3, A3, C3, E3, A3, F3, A3, D3)",
                        "eqangle(C3, A3, C3, E3, A3, F3, A3, D3)",
                        "ncoll(C3, A3, E3)"
                    ],
                    "head": "eqangle(A3, C3, A3, E3, F3, A3, F3, D3)"
                },
                {
                    "body": [
                        "eqangle(A3, C3, A3, E3, F3, A3, F3, D3)",
                        "coll(A3, B3, F3)"
                    ],
                    "head": "eqangle(A3, B3, A3, C3, D3, F3, A3, E3)"
                },
                {
                    "body": [
                        "eqangle(A3, E3, D3, F3, B3, C3, A3, D3)",
                        "eqangle(A3, B3, A3, C3, B3, C3, A3, D3)",
                        "eqangle(A3, B3, A3, C3, D3, F3, A3, E3)"
                    ],
                    "head": "perp(D3, F3, A3, E3)"
                },
                {
                    "body": [
                        "cong(A4, B4, A4, C4)",
                        "cong(D4, C4, D4, B4)"
                    ],
                    "head": "perp(B4, C4, A4, D4)"
                },
                {
                    "body": [
                        "cong(C4, A4, C4, E4)",
                        "cong(A4, F4, A4, D4)"
                    ],
                    "head": "eqratio(C4, A4, C4, E4, A4, F4, A4, D4)"
                },
                {
                    "body": [
                        "coll(E4, B4, C4)"
                    ],
                    "head": "coll(C4, E4, B4)"
                },
                {
                    "body": [
                        "coll(A4, B4, F4)"
                    ],
                    "head": "coll(A4, F4, B4)"
                },
                {
                    "body": [
                        "coll(B4, D4, C4)",
                        "cong(D4, C4, D4, B4)"
                    ],
                    "head": "midp(D4, C4, B4)"
                },
                {
                    "body": [
                        "perp(A4, B4, A4, C4)",
                        "midp(D4, C4, B4)"
                    ],
                    "head": "cong(C4, D4, A4, D4)"
                },
                {
                    "body": [
                        "perp(A4, B4, A4, C4)",
                        "midp(D4, C4, B4)"
                    ],
                    "head": "cong(B4, D4, A4, D4)"
                },
                {
                    "body": [
                        "cong(A4, B4, A4, C4)",
                        "cong(C4, D4, A4, D4)",
                        "cong(B4, D4, A4, D4)",
                        "ncoll(A4, C4, D4)"
                    ],
                    "head": "eqangle(C4, A4, C4, D4, A4, B4, A4, D4)"
                },
                {
                    "body": [
                        "eqangle(C4, A4, C4, D4, A4, B4, A4, D4)",
                        "coll(B4, D4, C4)"
                    ],
                    "head": "eqangle(A4, C4, B4, C4, A4, B4, A4, D4)"
                },
                {
                    "body": [
                        "coll(C4, E4, B4)",
                        "coll(A4, F4, B4)",
                        "eqangle(A4, C4, B4, C4, A4, B4, A4, D4)"
                    ],
                    "head": "eqangle(C4, A4, C4, E4, A4, F4, A4, D4)"
                },
                {
                    "body": [
                        "eqratio(C4, A4, C4, E4, A4, F4, A4, D4)",
                        "eqangle(C4, A4, C4, E4, A4, F4, A4, D4)",
                        "ncoll(C4, A4, E4)"
                    ],
                    "head": "eqangle(E4, A4, E4, C4, D4, F4, D4, A4)"
                },
                {
                    "body": [
                        "eqangle(E4, A4, E4, C4, D4, F4, D4, A4)",
                        "coll(E4, B4, C4)"
                    ],
                    "head": "eqangle(A4, E4, D4, F4, B4, C4, A4, D4)"
                },
                {
                    "body": [
                        "cong(A4, B4, A4, C4)",
                        "cong(C4, D4, A4, D4)",
                        "cong(B4, D4, A4, D4)",
                        "ncoll(A4, C4, D4)"
                    ],
                    "head": "eqangle(A4, C4, A4, D4, B4, A4, B4, D4)"
                },
                {
                    "body": [
                        "eqangle(A4, C4, A4, D4, B4, A4, B4, D4)",
                        "coll(B4, D4, C4)"
                    ],
                    "head": "eqangle(A4, B4, A4, C4, B4, C4, A4, D4)"
                },
                {
                    "body": [
                        "eqratio(C4, A4, C4, E4, A4, F4, A4, D4)",
                        "eqangle(C4, A4, C4, E4, A4, F4, A4, D4)",
                        "ncoll(C4, A4, E4)"
                    ],
                    "head": "eqangle(A4, C4, A4, E4, F4, A4, F4, D4)"
                },
                {
                    "body": [
                        "eqangle(A4, C4, A4, E4, F4, A4, F4, D4)",
                        "coll(A4, B4, F4)"
                    ],
                    "head": "eqangle(A4, B4, A4, C4, D4, F4, A4, E4)"
                },
                {
                    "body": [
                        "eqangle(A4, E4, D4, F4, B4, C4, A4, D4)",
                        "eqangle(A4, B4, A4, C4, B4, C4, A4, D4)",
                        "eqangle(A4, B4, A4, C4, D4, F4, A4, E4)"
                    ],
                    "head": "perp(D4, F4, A4, E4)"
                },
                {
                    "body": [
                        "cong(A5, B5, A5, C5)",
                        "cong(D5, C5, D5, B5)"
                    ],
                    "head": "perp(B5, C5, A5, D5)"
                },
                {
                    "body": [
                        "cong(C5, A5, C5, E5)",
                        "cong(A5, F5, A5, D5)"
                    ],
                    "head": "eqratio(C5, A5, C5, E5, A5, F5, A5, D5)"
                },
                {
                    "body": [
                        "coll(E5, B5, C5)"
                    ],
                    "head": "coll(C5, E5, B5)"
                },
                {
                    "body": [
                        "coll(A5, B5, F5)"
                    ],
                    "head": "coll(A5, F5, B5)"
                },
                {
                    "body": [
                        "coll(B5, D5, C5)",
                        "cong(D5, C5, D5, B5)"
                    ],
                    "head": "midp(D5, C5, B5)"
                },
                {
                    "body": [
                        "perp(A5, B5, A5, C5)",
                        "midp(D5, C5, B5)"
                    ],
                    "head": "cong(C5, D5, A5, D5)"
                },
                {
                    "body": [
                        "perp(A5, B5, A5, C5)",
                        "midp(D5, C5, B5)"
                    ],
                    "head": "cong(B5, D5, A5, D5)"
                },
                {
                    "body": [
                        "cong(A5, B5, A5, C5)",
                        "cong(C5, D5, A5, D5)",
                        "cong(B5, D5, A5, D5)",
                        "ncoll(A5, C5, D5)"
                    ],
                    "head": "eqangle(C5, A5, C5, D5, A5, B5, A5, D5)"
                },
                {
                    "body": [
                        "eqangle(C5, A5, C5, D5, A5, B5, A5, D5)",
                        "coll(B5, D5, C5)"
                    ],
                    "head": "eqangle(A5, C5, B5, C5, A5, B5, A5, D5)"
                },
                {
                    "body": [
                        "coll(C5, E5, B5)",
                        "coll(A5, F5, B5)",
                        "eqangle(A5, C5, B5, C5, A5, B5, A5, D5)"
                    ],
                    "head": "eqangle(C5, A5, C5, E5, A5, F5, A5, D5)"
                },
                {
                    "body": [
                        "eqratio(C5, A5, C5, E5, A5, F5, A5, D5)",
                        "eqangle(C5, A5, C5, E5, A5, F5, A5, D5)",
                        "ncoll(C5, A5, E5)"
                    ],
                    "head": "eqangle(E5, A5, E5, C5, D5, F5, D5, A5)"
                },
                {
                    "body": [
                        "eqangle(E5, A5, E5, C5, D5, F5, D5, A5)",
                        "coll(E5, B5, C5)"
                    ],
                    "head": "eqangle(A5, E5, D5, F5, B5, C5, A5, D5)"
                },
                {
                    "body": [
                        "cong(A5, B5, A5, C5)",
                        "cong(C5, D5, A5, D5)",
                        "cong(B5, D5, A5, D5)",
                        "ncoll(A5, C5, D5)"
                    ],
                    "head": "eqangle(A5, C5, A5, D5, B5, A5, B5, D5)"
                },
                {
                    "body": [
                        "eqangle(A5, C5, A5, D5, B5, A5, B5, D5)",
                        "coll(B5, D5, C5)"
                    ],
                    "head": "eqangle(A5, B5, A5, C5, B5, C5, A5, D5)"
                },
                {
                    "body": [
                        "eqratio(C5, A5, C5, E5, A5, F5, A5, D5)",
                        "eqangle(C5, A5, C5, E5, A5, F5, A5, D5)",
                        "ncoll(C5, A5, E5)"
                    ],
                    "head": "eqangle(A5, C5, A5, E5, F5, A5, F5, D5)"
                },
                {
                    "body": [
                        "eqangle(A5, C5, A5, E5, F5, A5, F5, D5)",
                        "coll(A5, B5, F5)"
                    ],
                    "head": "eqangle(A5, B5, A5, C5, D5, F5, A5, E5)"
                },
                {
                    "body": [
                        "eqangle(A5, E5, D5, F5, B5, C5, A5, D5)",
                        "eqangle(A5, B5, A5, C5, B5, C5, A5, D5)",
                        "eqangle(A5, B5, A5, C5, D5, F5, A5, E5)"
                    ],
                    "head": "perp(D5, F5, A5, E5)"
                },
                {
                    "body": [
                        "cong(A6, B6, A6, C6)",
                        "cong(D6, C6, D6, B6)"
                    ],
                    "head": "perp(B6, C6, A6, D6)"
                },
                {
                    "body": [
                        "cong(C6, A6, C6, E6)",
                        "cong(A6, F6, A6, D6)"
                    ],
                    "head": "eqratio(C6, A6, C6, E6, A6, F6, A6, D6)"
                },
                {
                    "body": [
                        "coll(E6, B6, C6)"
                    ],
                    "head": "coll(C6, E6, B6)"
                },
                {
                    "body": [
                        "coll(A6, B6, F6)"
                    ],
                    "head": "coll(A6, F6, B6)"
                },
                {
                    "body": [
                        "coll(B6, D6, C6)",
                        "cong(D6, C6, D6, B6)"
                    ],
                    "head": "midp(D6, C6, B6)"
                },
                {
                    "body": [
                        "perp(A6, B6, A6, C6)",
                        "midp(D6, C6, B6)"
                    ],
                    "head": "cong(C6, D6, A6, D6)"
                },
                {
                    "body": [
                        "perp(A6, B6, A6, C6)",
                        "midp(D6, C6, B6)"
                    ],
                    "head": "cong(B6, D6, A6, D6)"
                },
                {
                    "body": [
                        "cong(A6, B6, A6, C6)",
                        "cong(C6, D6, A6, D6)",
                        "cong(B6, D6, A6, D6)",
                        "ncoll(A6, C6, D6)"
                    ],
                    "head": "eqangle(C6, A6, C6, D6, A6, B6, A6, D6)"
                },
                {
                    "body": [
                        "eqangle(C6, A6, C6, D6, A6, B6, A6, D6)",
                        "coll(B6, D6, C6)"
                    ],
                    "head": "eqangle(A6, C6, B6, C6, A6, B6, A6, D6)"
                },
                {
                    "body": [
                        "coll(C6, E6, B6)",
                        "coll(A6, F6, B6)",
                        "eqangle(A6, C6, B6, C6, A6, B6, A6, D6)"
                    ],
                    "head": "eqangle(C6, A6, C6, E6, A6, F6, A6, D6)"
                },
                {
                    "body": [
                        "eqratio(C6, A6, C6, E6, A6, F6, A6, D6)",
                        "eqangle(C6, A6, C6, E6, A6, F6, A6, D6)",
                        "ncoll(C6, A6, E6)"
                    ],
                    "head": "eqangle(E6, A6, E6, C6, D6, F6, D6, A6)"
                },
                {
                    "body": [
                        "eqangle(E6, A6, E6, C6, D6, F6, D6, A6)",
                        "coll(E6, B6, C6)"
                    ],
                    "head": "eqangle(A6, E6, D6, F6, B6, C6, A6, D6)"
                },
                {
                    "body": [
                        "cong(A6, B6, A6, C6)",
                        "cong(C6, D6, A6, D6)",
                        "cong(B6, D6, A6, D6)",
                        "ncoll(A6, C6, D6)"
                    ],
                    "head": "eqangle(A6, C6, A6, D6, B6, A6, B6, D6)"
                },
                {
                    "body": [
                        "eqangle(A6, C6, A6, D6, B6, A6, B6, D6)",
                        "coll(B6, D6, C6)"
                    ],
                    "head": "eqangle(A6, B6, A6, C6, B6, C6, A6, D6)"
                },
                {
                    "body": [
                        "eqratio(C6, A6, C6, E6, A6, F6, A6, D6)",
                        "eqangle(C6, A6, C6, E6, A6, F6, A6, D6)",
                        "ncoll(C6, A6, E6)"
                    ],
                    "head": "eqangle(A6, C6, A6, E6, F6, A6, F6, D6)"
                },
                {
                    "body": [
                        "eqangle(A6, C6, A6, E6, F6, A6, F6, D6)",
                        "coll(A6, B6, F6)"
                    ],
                    "head": "eqangle(A6, B6, A6, C6, D6, F6, A6, E6)"
                },
                {
                    "body": [
                        "eqangle(A6, E6, D6, F6, B6, C6, A6, D6)",
                        "eqangle(A6, B6, A6, C6, B6, C6, A6, D6)",
                        "eqangle(A6, B6, A6, C6, D6, F6, A6, E6)"
                    ],
                    "head": "perp(D6, F6, A6, E6)"
                },
                {
                    "body": [
                        "cong(A7, B7, A7, C7)",
                        "cong(D7, C7, D7, B7)"
                    ],
                    "head": "perp(B7, C7, A7, D7)"
                },
                {
                    "body": [
                        "cong(C7, A7, C7, E7)",
                        "cong(A7, F7, A7, D7)"
                    ],
                    "head": "eqratio(C7, A7, C7, E7, A7, F7, A7, D7)"
                },
                {
                    "body": [
                        "coll(E7, B7, C7)"
                    ],
                    "head": "coll(C7, E7, B7)"
                },
                {
                    "body": [
                        "coll(A7, B7, F7)"
                    ],
                    "head": "coll(A7, F7, B7)"
                },
                {
                    "body": [
                        "coll(B7, D7, C7)",
                        "cong(D7, C7, D7, B7)"
                    ],
                    "head": "midp(D7, C7, B7)"
                },
                {
                    "body": [
                        "perp(A7, B7, A7, C7)",
                        "midp(D7, C7, B7)"
                    ],
                    "head": "cong(C7, D7, A7, D7)"
                },
                {
                    "body": [
                        "perp(A7, B7, A7, C7)",
                        "midp(D7, C7, B7)"
                    ],
                    "head": "cong(B7, D7, A7, D7)"
                },
                {
                    "body": [
                        "cong(A7, B7, A7, C7)",
                        "cong(C7, D7, A7, D7)",
                        "cong(B7, D7, A7, D7)",
                        "ncoll(A7, C7, D7)"
                    ],
                    "head": "eqangle(C7, A7, C7, D7, A7, B7, A7, D7)"
                },
                {
                    "body": [
                        "eqangle(C7, A7, C7, D7, A7, B7, A7, D7)",
                        "coll(B7, D7, C7)"
                    ],
                    "head": "eqangle(A7, C7, B7, C7, A7, B7, A7, D7)"
                },
                {
                    "body": [
                        "coll(C7, E7, B7)",
                        "coll(A7, F7, B7)",
                        "eqangle(A7, C7, B7, C7, A7, B7, A7, D7)"
                    ],
                    "head": "eqangle(C7, A7, C7, E7, A7, F7, A7, D7)"
                },
                {
                    "body": [
                        "eqratio(C7, A7, C7, E7, A7, F7, A7, D7)",
                        "eqangle(C7, A7, C7, E7, A7, F7, A7, D7)",
                        "ncoll(C7, A7, E7)"
                    ],
                    "head": "eqangle(E7, A7, E7, C7, D7, F7, D7, A7)"
                },
                {
                    "body": [
                        "eqangle(E7, A7, E7, C7, D7, F7, D7, A7)",
                        "coll(E7, B7, C7)"
                    ],
                    "head": "eqangle(A7, E7, D7, F7, B7, C7, A7, D7)"
                },
                {
                    "body": [
                        "cong(A7, B7, A7, C7)",
                        "cong(C7, D7, A7, D7)",
                        "cong(B7, D7, A7, D7)",
                        "ncoll(A7, C7, D7)"
                    ],
                    "head": "eqangle(A7, C7, A7, D7, B7, A7, B7, D7)"
                },
                {
                    "body": [
                        "eqangle(A7, C7, A7, D7, B7, A7, B7, D7)",
                        "coll(B7, D7, C7)"
                    ],
                    "head": "eqangle(A7, B7, A7, C7, B7, C7, A7, D7)"
                },
                {
                    "body": [
                        "eqratio(C7, A7, C7, E7, A7, F7, A7, D7)",
                        "eqangle(C7, A7, C7, E7, A7, F7, A7, D7)",
                        "ncoll(C7, A7, E7)"
                    ],
                    "head": "eqangle(A7, C7, A7, E7, F7, A7, F7, D7)"
                },
                {
                    "body": [
                        "eqangle(A7, C7, A7, E7, F7, A7, F7, D7)",
                        "coll(A7, B7, F7)"
                    ],
                    "head": "eqangle(A7, B7, A7, C7, D7, F7, A7, E7)"
                },
                {
                    "body": [
                        "eqangle(A7, E7, D7, F7, B7, C7, A7, D7)",
                        "eqangle(A7, B7, A7, C7, B7, C7, A7, D7)",
                        "eqangle(A7, B7, A7, C7, D7, F7, A7, E7)"
                    ],
                    "head": "perp(D7, F7, A7, E7)"
                }
            ]
        },
        "eval": {
            "background_knowledge": [
                "perp(A8, B8, A8, C8)",
                "cong(A8, B8, A8, C8)",
                "cong(D8, C8, D8, B8)",
                "coll(C8, B8, D8)",
                "ncoll(A8, C8, D8)",
                "cong(C8, A8, C8, E8)",
                "coll(E8, C8, B8)",
                "ncoll(C8, A8, E8)",
                "cong(A8, F8, A8, D8)",
                "coll(F8, A8, B8)",
                "perp(A9, B9, A9, C9)",
                "cong(A9, B9, A9, C9)",
                "cong(D9, C9, D9, B9)",
                "coll(C9, B9, D9)",
                "ncoll(A9, C9, D9)",
                "cong(C9, A9, C9, E9)",
                "coll(E9, C9, B9)",
                "ncoll(C9, A9, E9)",
                "cong(A9, F9, A9, D9)",
                "coll(F9, A9, B9)"
            ],
            "positive_examples": [
                "perp(B8, C8, A8, D8)",
                "perp(D8, F8, A8, E8)",
                "perp(B9, C9, A9, D9)",
                "perp(D9, F9, A9, E9)"
            ],
            "proof_steps": [
                {
                    "body": [
                        "cong(A8, B8, A8, C8)",
                        "cong(D8, C8, D8, B8)"
                    ],
                    "head": "perp(B8, C8, A8, D8)"
                },
                {
                    "body": [
                        "cong(C8, A8, C8, E8)",
                        "cong(A8, F8, A8, D8)"
                    ],
                    "head": "eqratio(C8, A8, C8, E8, A8, F8, A8, D8)"
                },
                {
                    "body": [
                        "coll(E8, C8, B8)"
                    ],
                    "head": "coll(C8, E8, B8)"
                },
                {
                    "body": [
                        "coll(F8, A8, B8)"
                    ],
                    "head": "coll(A8, F8, B8)"
                },
                {
                    "body": [
                        "coll(C8, B8, D8)",
                        "cong(D8, C8, D8, B8)"
                    ],
                    "head": "midp(D8, C8, B8)"
                },
                {
                    "body": [
                        "perp(A8, B8, A8, C8)",
                        "midp(D8, C8, B8)"
                    ],
                    "head": "cong(C8, D8, A8, D8)"
                },
                {
                    "body": [
                        "perp(A8, B8, A8, C8)",
                        "midp(D8, C8, B8)"
                    ],
                    "head": "cong(B8, D8, A8, D8)"
                },
                {
                    "body": [
                        "cong(A8, B8, A8, C8)",
                        "cong(C8, D8, A8, D8)",
                        "cong(B8, D8, A8, D8)",
                        "ncoll(A8, C8, D8)"
                    ],
                    "head": "eqangle(C8, A8, C8, D8, A8, B8, A8, D8)"
                },
                {
                    "body": [
                        "eqangle(C8, A8, C8, D8, A8, B8, A8, D8)",
                        "coll(C8, B8, D8)"
                    ],
                    "head": "eqangle(A8, C8, B8, C8, A8, B8, A8, D8)"
                },
                {
                    "body": [
                        "coll(C8, E8, B8)",
                        "coll(A8, F8, B8)",
                        "eqangle(A8, C8, B8, C8, A8, B8, A8, D8)"
                    ],
                    "head": "eqangle(C8, A8, C8, E8, A8, F8, A8, D8)"
                },
                {
                    "body": [
                        "eqratio(C8, A8, C8, E8, A8, F8, A8, D8)",
                        "eqangle(C8, A8, C8, E8, A8, F8, A8, D8)",
                        "ncoll(C8, A8, E8)"
                    ],
                    "head": "eqangle(E8, A8, E8, C8, D8, F8, D8, A8)"
                },
                {
                    "body": [
                        "eqangle(E8, A8, E8, C8, D8, F8, D8, A8)",
                        "coll(E8, C8, B8)"
                    ],
                    "head": "eqangle(A8, E8, D8, F8, B8, C8, A8, D8)"
                },
                {
                    "body": [
                        "cong(A8, B8, A8, C8)",
                        "cong(C8, D8, A8, D8)",
                        "cong(B8, D8, A8, D8)",
                        "ncoll(A8, C8, D8)"
                    ],
                    "head": "eqangle(A8, C8, A8, D8, B8, A8, B8, D8)"
                },
                {
                    "body": [
                        "eqangle(A8, C8, A8, D8, B8, A8, B8, D8)",
                        "coll(C8, B8, D8)"
                    ],
                    "head": "eqangle(A8, B8, A8, C8, B8, C8, A8, D8)"
                },
                {
                    "body": [
                        "eqratio(C8, A8, C8, E8, A8, F8, A8, D8)",
                        "eqangle(C8, A8, C8, E8, A8, F8, A8, D8)",
                        "ncoll(C8, A8, E8)"
                    ],
                    "head": "eqangle(A8, C8, A8, E8, F8, A8, F8, D8)"
                },
                {
                    "body": [
                        "eqangle(A8, C8, A8, E8, F8, A8, F8, D8)",
                        "coll(F8, A8, B8)"
                    ],
                    "head": "eqangle(A8, B8, A8, C8, D8, F8, A8, E8)"
                },
                {
                    "body": [
                        "eqangle(A8, E8, D8, F8, B8, C8, A8, D8)",
                        "eqangle(A8, B8, A8, C8, B8, C8, A8, D8)",
                        "eqangle(A8, B8, A8, C8, D8, F8, A8, E8)"
                    ],
                    "head": "perp(D8, F8, A8, E8)"
                },
                {
                    "body": [
                        "cong(A9, B9, A9, C9)",
                        "cong(D9, C9, D9, B9)"
                    ],
                    "head": "perp(B9, C9, A9, D9)"
                },
                {
                    "body": [
                        "cong(C9, A9, C9, E9)",
                        "cong(A9, F9, A9, D9)"
                    ],
                    "head": "eqratio(C9, A9, C9, E9, A9, F9, A9, D9)"
                },
                {
                    "body": [
                        "coll(E9, C9, B9)"
                    ],
                    "head": "coll(C9, E9, B9)"
                },
                {
                    "body": [
                        "coll(F9, A9, B9)"
                    ],
                    "head": "coll(A9, F9, B9)"
                },
                {
                    "body": [
                        "coll(C9, B9, D9)",
                        "cong(D9, C9, D9, B9)"
                    ],
                    "head": "midp(D9, C9, B9)"
                },
                {
                    "body": [
                        "perp(A9, B9, A9, C9)",
                        "midp(D9, C9, B9)"
                    ],
                    "head": "cong(C9, D9, A9, D9)"
                },
                {
                    "body": [
                        "perp(A9, B9, A9, C9)",
                        "midp(D9, C9, B9)"
                    ],
                    "head": "cong(B9, D9, A9, D9)"
                },
                {
                    "body": [
                        "cong(A9, B9, A9, C9)",
                        "cong(C9, D9, A9, D9)",
                        "cong(B9, D9, A9, D9)",
                        "ncoll(A9, C9, D9)"
                    ],
                    "head": "eqangle(C9, A9, C9, D9, A9, B9, A9, D9)"
                },
                {
                    "body": [
                        "eqangle(C9, A9, C9, D9, A9, B9, A9, D9)",
                        "coll(C9, B9, D9)"
                    ],
                    "head": "eqangle(A9, C9, B9, C9, A9, B9, A9, D9)"
                },
                {
                    "body": [
                        "coll(C9, E9, B9)",
                        "coll(A9, F9, B9)",
                        "eqangle(A9, C9, B9, C9, A9, B9, A9, D9)"
                    ],
                    "head": "eqangle(C9, A9, C9, E9, A9, F9, A9, D9)"
                },
                {
                    "body": [
                        "eqratio(C9, A9, C9, E9, A9, F9, A9, D9)",
                        "eqangle(C9, A9, C9, E9, A9, F9, A9, D9)",
                        "ncoll(C9, A9, E9)"
                    ],
                    "head": "eqangle(E9, A9, E9, C9, D9, F9, D9, A9)"
                },
                {
                    "body": [
                        "eqangle(E9, A9, E9, C9, D9, F9, D9, A9)",
                        "coll(E9, C9, B9)"
                    ],
                    "head": "eqangle(A9, E9, D9, F9, B9, C9, A9, D9)"
                },
                {
                    "body": [
                        "cong(A9, B9, A9, C9)",
                        "cong(C9, D9, A9, D9)",
                        "cong(B9, D9, A9, D9)",
                        "ncoll(A9, C9, D9)"
                    ],
                    "head": "eqangle(A9, C9, A9, D9, B9, A9, B9, D9)"
                },
                {
                    "body": [
                        "eqangle(A9, C9, A9, D9, B9, A9, B9, D9)",
                        "coll(C9, B9, D9)"
                    ],
                    "head": "eqangle(A9, B9, A9, C9, B9, C9, A9, D9)"
                },
                {
                    "body": [
                        "eqratio(C9, A9, C9, E9, A9, F9, A9, D9)",
                        "eqangle(C9, A9, C9, E9, A9, F9, A9, D9)",
                        "ncoll(C9, A9, E9)"
                    ],
                    "head": "eqangle(A9, C9, A9, E9, F9, A9, F9, D9)"
                },
                {
                    "body": [
                        "eqangle(A9, C9, A9, E9, F9, A9, F9, D9)",
                        "coll(F9, A9, B9)"
                    ],
                    "head": "eqangle(A9, B9, A9, C9, D9, F9, A9, E9)"
                },
                {
                    "body": [
                        "eqangle(A9, E9, D9, F9, B9, C9, A9, D9)",
                        "eqangle(A9, B9, A9, C9, B9, C9, A9, D9)",
                        "eqangle(A9, B9, A9, C9, D9, F9, A9, E9)"
                    ],
                    "head": "perp(D9, F9, A9, E9)"
                }
            ]
        }
    }
}